tests/__init__.py
tests/test_dataset.py
tests/test_duplicates.py
tests/test_eda_plots.py
tests/test_eda_report.py
tests/test_quality.py
viz_scout/__init__.py
viz_scout/__version__.py
viz_scout/corruption.py
viz_scout/dataset.py
viz_scout/duplicates.py
viz_scout/eda_plots.py
viz_scout/eda_report.py
viz_scout/quality.py
viz_scout/utils.py
viz_scout-0.2.7.dist-info/LICENSE
viz_scout-0.2.7.dist-info/METADATA
viz_scout-0.2.7.dist-info/WHEEL
viz_scout-0.2.7.dist-info/top_level.txt
viz_scout-0.2.7.dist-info/RECORD
