Metadata-Version: 2.2
Name: viz_scout
Version: 0.2.7
Summary: A Python toolkit for end-to-end image analysis with cloud (Minio, S3) support.
Home-page: https://github.com/iitm-rohandhatbale/viz_scout
Author: Rohan Dhatbale
Author-email: rohandhatbale@gmail.com
Classifier: Programming Language :: Python :: 3
Classifier: License :: OSI Approved :: MIT License
Classifier: Operating System :: OS Independent
Requires-Python: >=3.8
License-File: LICENSE
Requires-Dist: opencv-python
Requires-Dist: numpy
Requires-Dist: tqdm
Requires-Dist: pillow
Requires-Dist: boto3
Requires-Dist: minio
Requires-Dist: imagededup
Requires-Dist: icecream
Requires-Dist: altair
Requires-Dist: pandas
Requires-Dist: vl-convert-python
Dynamic: author
Dynamic: author-email
Dynamic: classifier
Dynamic: description
Dynamic: description-content-type
Dynamic: home-page
Dynamic: requires-dist
Dynamic: requires-python
Dynamic: summary
